[
    {
        "id": "JOB-2025-001",
        "customer": "Rajesh Kumar",
        "mobile": "9876543210",
        "email": "rajesh.kumar@gmail.com",
        "address": "45 Satellite Road, Surat",
        "device": "Dell Inspiron 15",
        "serial": "DL123456789",
        "issue": "Screen flickering, battery not charging. Customer reports issue started 2 days ago.",
        "serviceType": "Insite",
        "department": "Laptop Service",
        "departmentId": 2,
        "priority": "High",
        "status": "In Progress",
        "assignedTo": "Amit Patel",
        "assignedToId": 3,
        "estimatedCompletion": "2025-12-18",
        "amcId": "AMC-2024-001",
        "isAMCCovered": true,
        "partsUsed": [
            {
                "itemId": 15,
                "name": "Laptop Battery Dell",
                "qty": 1,
                "price": 3500,
                "gst": 18
            }
        ],
        "servicesApplied": [
            {
                "addonId": 1,
                "name": "General Service (Laptop)",
                "originalPrice": 350,
                "price": 350,
                "gst": 18,
                "isChargeable": false
            }
        ],
        "baseCharge": 300,
        "createdDate": "2025-11-28",
        "completedDate": null,
        "deliveredDate": null,
        "notes": ""
    },
    {
        "id": "JOB-2025-002",
        "customer": "Sneha Sharma",
        "mobile": "9123456789",
        "email": "sneha.sharma@email.com",
        "address": "123 Ring Road, Surat",
        "device": "HP Pavilion Desktop",
        "serial": "HP987654321",
        "issue": "No display, motherboard issue suspected. Tried different monitors.",
        "serviceType": "Outsite",
        "department": "Computer Service",
        "departmentId": 1,
        "priority": "Medium",
        "status": "Pending Parts",
        "assignedTo": "Vikram Malhotra",
        "assignedToId": 5,
        "estimatedCompletion": "2025-12-20",
        "amcId": null,
        "isAMCCovered": false,
        "partsUsed": [],
        "servicesApplied": [
            {
                "addonId": 5,
                "name": "Chip Level Repair (Motherboard)",
                "originalPrice": 2500,
                "price": 2500,
                "gst": 18,
                "isChargeable": true
            }
        ],
        "baseCharge": 500,
        "createdDate": "2025-11-27",
        "completedDate": null,
        "deliveredDate": null,
        "notes": "Waiting for replacement IC chip"
    },
    {
        "id": "JOB-2025-003",
        "customer": "Tech Corp Ltd",
        "mobile": "9988776655",
        "email": "tech.corp@email.com",
        "address": "456 Business Park, Surat",
        "device": "Lenovo ThinkPad X1",
        "serial": "LN456789123",
        "issue": "Software installation and configuration - Windows 11 Pro with Office Suite.",
        "serviceType": "Remote",
        "department": "Laptop Service",
        "departmentId": 2,
        "priority": "Low",
        "status": "Completed",
        "assignedTo": "Amit Patel",
        "assignedToId": 3,
        "estimatedCompletion": "2025-11-26",
        "amcId": null,
        "isAMCCovered": false,
        "partsUsed": [],
        "servicesApplied": [
            {
                "addonId": 2,
                "name": "OS Installation (Windows 10/11)",
                "originalPrice": 500,
                "price": 500,
                "gst": 18,
                "isChargeable": true
            }
        ],
        "baseCharge": 200,
        "createdDate": "2025-11-26",
        "completedDate": "2025-11-26",
        "deliveredDate": null,
        "notes": ""
    },
    {
        "id": "JOB-2025-004",
        "customer": "Priya Patel",
        "mobile": "9876500000",
        "email": "priya.patel@company.com",
        "address": "789 Tech Hub, Surat",
        "device": "Asus ROG Gaming Laptop",
        "serial": "AS789456123",
        "issue": "Overheating and loud fan noise during gaming. Thermal throttling suspected.",
        "serviceType": "Insite",
        "department": "Laptop Service",
        "departmentId": 2,
        "priority": "High",
        "status": "Open",
        "assignedTo": null,
        "assignedToId": null,
        "estimatedCompletion": "",
        "amcId": null,
        "isAMCCovered": false,
        "partsUsed": [],
        "servicesApplied": [],
        "baseCharge": 0,
        "createdDate": "2025-11-29",
        "completedDate": null,
        "deliveredDate": null,
        "notes": ""
    },
    {
        "id": "JOB-2025-005",
        "customer": "GlobalTech Industries",
        "mobile": "9876543210",
        "email": "purchase@globaltech.in",
        "address": "Industrial Area, Phase 2, Surat",
        "device": "Dell Workstation T5820",
        "serial": "DELL-WS-2025-005678",
        "issue": "Regular preventive maintenance and system optimization as per AMC schedule.",
        "serviceType": "Outsite",
        "department": "Field Service",
        "departmentId": 4,
        "priority": "Low",
        "status": "Delivered",
        "assignedTo": "Vikram Malhotra",
        "assignedToId": 5,
        "estimatedCompletion": "2025-12-10",
        "amcId": "AMC-2025-002",
        "isAMCCovered": true,
        "partsUsed": [],
        "servicesApplied": [
            {
                "addonId": 1,
                "name": "General Service (Laptop)",
                "originalPrice": 350,
                "price": 350,
                "gst": 18,
                "isChargeable": false
            }
        ],
        "baseCharge": 0,
        "createdDate": "2025-12-08",
        "completedDate": "2025-12-10",
        "deliveredDate": "2025-12-10",
        "notes": "AMC scheduled maintenance completed"
    }
]